{
  "annotations": {
    "list": [
      {
        "builtIn": 1,
        "datasource": "-- Grafana --",
        "enable": true,
        "hide": true,
        "iconColor": "rgba(0, 211, 255, 1)",
        "name": "Annotations & Alerts",
        "type": "dashboard"
      }
    ]
  },
  "description": "Global Kafka dashboard running on Kubernetes. Support  Bitnami Kafka chart https://github.com/bitnami/charts/tree/master/bitnami/kafka ",
  "editable": true,
  "gnetId": 12483,
  "graphTooltip": 0,
  "id": 141,
  "iteration": 1602559644580,
  "links": [],
  "panels": [
    {
      "collapsed": false,
      "datasource": "Prometheus",
      "gridPos": {
        "h": 1,
        "w": 24,
        "x": 0,
        "y": 0
      },
      "id": 10,
      "panels": [],
      "title": "General",
      "type": "row"
    },
    {
      "cacheTimeout": null,
      "colorBackground": false,
      "colorValue": false,
      "colors": [
        "#299c46",
        "rgba(237, 129, 40, 0.89)",
        "#d44a3a"
      ],
      "datasource": "$datasource",
      "fieldConfig": {
        "defaults": {
          "custom": {}
        },
        "overrides": []
      },
      "format": "none",
      "gauge": {
        "maxValue": 100,
        "minValue": 0,
        "show": false,
        "thresholdLabels": false,
        "thresholdMarkers": true
      },
      "gridPos": {
        "h": 3,
        "w": 4,
        "x": 0,
        "y": 1
      },
      "id": 2,
      "interval": null,
      "links": [],
      "mappingType": 1,
      "mappingTypes": [
        {
          "name": "value to text",
          "value": 1
        },
        {
          "name": "range to text",
          "value": 2
        }
      ],
      "maxDataPoints": 100,
      "nullPointMode": "connected",
      "nullText": null,
      "postfix": "",
      "postfixFontSize": "50%",
      "prefix": "",
      "prefixFontSize": "50%",
      "rangeMaps": [
        {
          "from": "null",
          "text": "N/A",
          "to": "null"
        }
      ],
      "sparkline": {
        "fillColor": "rgba(31, 118, 189, 0.18)",
        "full": true,
        "lineColor": "rgb(31, 120, 193)",
        "show": true
      },
      "tableColumn": "kafka_brokers{endpoint=\"metrics\", instance=\"my-kafka-cluster\", job=\"kafka-exporter\", namespace=\"infra\", pod=\"kafka-exporter-54d7988676-7qtvb\", service=\"kafka-exporter\"}",
      "targets": [
        {
          "expr": "kafka_brokers",
          "format": "time_series",
          "instant": false,
          "intervalFactor": 1,
          "refId": "A"
        }
      ],
      "thresholds": "",
      "title": "Number of brokers",
      "type": "singlestat",
      "valueFontSize": "80%",
      "valueMaps": [
        {
          "op": "=",
          "text": "N/A",
          "value": "null"
        }
      ],
      "valueName": "current"
    },
    {
      "cacheTimeout": null,
      "colorBackground": true,
      "colorValue": false,
      "colors": [
        "#299c46",
        "rgba(237, 129, 40, 0.89)",
        "#d44a3a"
      ],
      "datasource": "$datasource",
      "fieldConfig": {
        "defaults": {
          "custom": {}
        },
        "overrides": []
      },
      "format": "none",
      "gauge": {
        "maxValue": 100,
        "minValue": 0,
        "show": false,
        "thresholdLabels": false,
        "thresholdMarkers": true
      },
      "gridPos": {
        "h": 6,
        "w": 4,
        "x": 4,
        "y": 1
      },
      "id": 20,
      "interval": null,
      "links": [],
      "mappingType": 2,
      "mappingTypes": [
        {
          "name": "value to text",
          "value": 1
        },
        {
          "name": "range to text",
          "value": 2
        }
      ],
      "maxDataPoints": 100,
      "nullPointMode": "connected",
      "nullText": null,
      "postfix": "",
      "postfixFontSize": "50%",
      "prefix": "",
      "prefixFontSize": "50%",
      "rangeMaps": [
        {
          "from": "0",
          "text": "OK",
          "to": "0"
        },
        {
          "from": "1",
          "text": "KO",
          "to": "9999999999"
        }
      ],
      "sparkline": {
        "fillColor": "rgba(31, 118, 189, 0.18)",
        "full": false,
        "lineColor": "rgb(31, 120, 193)",
        "show": false
      },
      "tableColumn": "",
      "targets": [
        {
          "expr": "sum(kafka_controller_controllerstats_uncleanleaderelectionspersec_count{instance=~\"$broker\"})",
          "format": "time_series",
          "instant": true,
          "intervalFactor": 1,
          "refId": "A"
        }
      ],
      "thresholds": "1,1",
      "title": "Unclean leader election",
      "type": "singlestat",
      "valueFontSize": "80%",
      "valueMaps": [
        {
          "op": "=",
          "text": "OK",
          "value": "0"
        },
        {
          "op": "=",
          "text": "",
          "value": ""
        }
      ],
      "valueName": "current"
    },
    {
      "cacheTimeout": null,
      "colorBackground": true,
      "colorValue": false,
      "colors": [
        "#d44a3a",
        "#299c46",
        "#d44a3a"
      ],
      "datasource": "$datasource",
      "fieldConfig": {
        "defaults": {
          "custom": {}
        },
        "overrides": []
      },
      "format": "none",
      "gauge": {
        "maxValue": 100,
        "minValue": 0,
        "show": false,
        "thresholdLabels": false,
        "thresholdMarkers": true
      },
      "gridPos": {
        "h": 6,
        "w": 4,
        "x": 8,
        "y": 1
      },
      "id": 60,
      "interval": null,
      "links": [],
      "mappingType": 2,
      "mappingTypes": [
        {
          "name": "value to text",
          "value": 1
        },
        {
          "name": "range to text",
          "value": 2
        }
      ],
      "maxDataPoints": 100,
      "nullPointMode": "connected",
      "nullText": null,
      "postfix": "",
      "postfixFontSize": "50%",
      "prefix": "",
      "prefixFontSize": "50%",
      "rangeMaps": [
        {
          "from": "-9999999999",
          "text": "KO",
          "to": "0"
        },
        {
          "from": "1",
          "text": "OK",
          "to": "1"
        },
        {
          "from": "2",
          "text": "KO",
          "to": "9999999999"
        }
      ],
      "sparkline": {
        "fillColor": "rgba(31, 118, 189, 0.18)",
        "full": false,
        "lineColor": "rgb(31, 120, 193)",
        "show": false
      },
      "tableColumn": "",
      "targets": [
        {
          "expr": "sum(kafka_controller_kafkacontroller_activecontrollercount_value)",
          "format": "time_series",
          "instant": true,
          "interval": "",
          "intervalFactor": 1,
          "legendFormat": "",
          "refId": "A"
        }
      ],
      "thresholds": "1,2",
      "title": "Active controller status",
      "type": "singlestat",
      "valueFontSize": "80%",
      "valueMaps": [
        {
          "op": "=",
          "text": "N/A",
          "value": "-9999999"
        }
      ],
      "valueName": "current"
    },
    {
      "cacheTimeout": null,
      "colorBackground": true,
      "colorValue": false,
      "colors": [
        "#d44a3a",
        "rgba(237, 129, 40, 0.89)",
        "#299c46"
      ],
      "datasource": "$datasource",
      "fieldConfig": {
        "defaults": {
          "custom": {}
        },
        "overrides": []
      },
      "format": "none",
      "gauge": {
        "maxValue": 100,
        "minValue": 0,
        "show": false,
        "thresholdLabels": false,
        "thresholdMarkers": true
      },
      "gridPos": {
        "h": 3,
        "w": 4,
        "x": 12,
        "y": 1
      },
      "id": 63,
      "interval": null,
      "links": [],
      "mappingType": 1,
      "mappingTypes": [
        {
          "name": "value to text",
          "value": 1
        },
        {
          "name": "range to text",
          "value": 2
        }
      ],
      "maxDataPoints": 100,
      "nullPointMode": "connected",
      "nullText": null,
      "postfix": "",
      "postfixFontSize": "50%",
      "prefix": "",
      "prefixFontSize": "50%",
      "rangeMaps": [
        {
          "from": "null",
          "text": "N/A",
          "to": "null"
        }
      ],
      "sparkline": {
        "fillColor": "rgba(31, 118, 189, 0.18)",
        "full": false,
        "lineColor": "rgb(31, 120, 193)",
        "show": false
      },
      "tableColumn": "",
      "targets": [
        {
          "expr": "- sum(kafka_server_replicamanager_total_isrshrinkspersec_count{instance=~\"$broker\"})",
          "format": "time_series",
          "instant": true,
          "interval": "",
          "intervalFactor": 1,
          "legendFormat": "",
          "refId": "A"
        }
      ],
      "thresholds": "0,0",
      "title": "In-sync replicas shrinks",
      "type": "singlestat",
      "valueFontSize": "80%",
      "valueMaps": [
        {
          "op": "=",
          "text": "N/A",
          "value": "null"
        }
      ],
      "valueName": "current"
    },
    {
      "cacheTimeout": null,
      "colorBackground": true,
      "colorValue": false,
      "colors": [
        "#299c46",
        "rgba(237, 129, 40, 0.89)",
        "#d44a3a"
      ],
      "datasource": "$datasource",
      "fieldConfig": {
        "defaults": {
          "custom": {}
        },
        "overrides": []
      },
      "format": "none",
      "gauge": {
        "maxValue": 100,
        "minValue": 0,
        "show": false,
        "thresholdLabels": false,
        "thresholdMarkers": true
      },
      "gridPos": {
        "h": 3,
        "w": 4,
        "x": 16,
        "y": 1
      },
      "id": 6,
      "interval": null,
      "links": [],
      "mappingType": 1,
      "mappingTypes": [
        {
          "name": "value to text",
          "value": 1
        },
        {
          "name": "range to text",
          "value": 2
        }
      ],
      "maxDataPoints": 100,
      "nullPointMode": "connected",
      "nullText": null,
      "postfix": "",
      "postfixFontSize": "50%",
      "prefix": "",
      "prefixFontSize": "50%",
      "rangeMaps": [
        {
          "from": "null",
          "text": "N/A",
          "to": "null"
        }
      ],
      "sparkline": {
        "fillColor": "rgba(31, 118, 189, 0.18)",
        "full": false,
        "lineColor": "rgb(31, 120, 193)",
        "show": false
      },
      "tableColumn": "",
      "targets": [
        {
          "expr": "sum(kafka_topic_partition_under_replicated_partition)",
          "format": "time_series",
          "instant": true,
          "intervalFactor": 1,
          "refId": "A"
        }
      ],
      "thresholds": "1,1",
      "title": "Under replicated partitions",
      "type": "singlestat",
      "valueFontSize": "80%",
      "valueMaps": [
        {
          "op": "=",
          "text": "N/A",
          "value": "null"
        }
      ],
      "valueName": "current"
    },
    {
      "cacheTimeout": null,
      "colorBackground": false,
      "colorValue": false,
      "colors": [
        "#299c46",
        "rgba(237, 129, 40, 0.89)",
        "#d44a3a"
      ],
      "datasource": "$datasource",
      "fieldConfig": {
        "defaults": {
          "custom": {}
        },
        "overrides": []
      },
      "format": "none",
      "gauge": {
        "maxValue": 100,
        "minValue": 0,
        "show": false,
        "thresholdLabels": false,
        "thresholdMarkers": true
      },
      "gridPos": {
        "h": 6,
        "w": 4,
        "x": 20,
        "y": 1
      },
      "id": 30,
      "interval": null,
      "links": [],
      "mappingType": 1,
      "mappingTypes": [
        {
          "name": "value to text",
          "value": 1
        },
        {
          "name": "range to text",
          "value": 2
        }
      ],
      "maxDataPoints": 100,
      "nullPointMode": "connected",
      "nullText": null,
      "postfix": "",
      "postfixFontSize": "50%",
      "prefix": "",
      "prefixFontSize": "50%",
      "rangeMaps": [
        {
          "from": "null",
          "text": "N/A",
          "to": "null"
        }
      ],
      "sparkline": {
        "fillColor": "rgba(31, 118, 189, 0.18)",
        "full": true,
        "lineColor": "rgb(31, 120, 193)",
        "show": true
      },
      "tableColumn": "kafka_server_replicamanager_total_partitioncount_value{endpoint=\"http-metrics\", instance=\"my-kafka-cluster\", job=\"kafka-jmx-exporter-jmx-metrics\", namespace=\"infra\", pod=\"kafka-jmx-exporter-jmx-exporter-84cc544b8f-mqznv\", service=\"kafka-jmx-exporter-jmx-metrics\"}",
      "targets": [
        {
          "expr": "kafka_server_replicamanager_total_partitioncount_value{instance=~\"$broker\"}",
          "format": "time_series",
          "instant": false,
          "interval": "",
          "intervalFactor": 1,
          "legendFormat": "",
          "refId": "A"
        }
      ],
      "thresholds": "",
      "title": "Partition count",
      "type": "singlestat",
      "valueFontSize": "80%",
      "valueMaps": [
        {
          "op": "=",
          "text": "INVALID BROKER",
          "value": "null"
        }
      ],
      "valueName": "current"
    },
    {
      "cacheTimeout": null,
      "colorBackground": false,
      "colorValue": false,
      "colors": [
        "#299c46",
        "rgba(237, 129, 40, 0.89)",
        "#d44a3a"
      ],
      "datasource": "$datasource",
      "fieldConfig": {
        "defaults": {
          "custom": {}
        },
        "overrides": []
      },
      "format": "none",
      "gauge": {
        "maxValue": 100,
        "minValue": 0,
        "show": false,
        "thresholdLabels": false,
        "thresholdMarkers": true
      },
      "gridPos": {
        "h": 3,
        "w": 4,
        "x": 0,
        "y": 4
      },
      "id": 4,
      "interval": null,
      "links": [],
      "mappingType": 1,
      "mappingTypes": [
        {
          "name": "value to text",
          "value": 1
        },
        {
          "name": "range to text",
          "value": 2
        }
      ],
      "maxDataPoints": 100,
      "nullPointMode": "connected",
      "nullText": null,
      "postfix": "",
      "postfixFontSize": "50%",
      "prefix": "",
      "prefixFontSize": "50%",
      "rangeMaps": [
        {
          "from": "null",
          "text": "N/A",
          "to": "null"
        }
      ],
      "sparkline": {
        "fillColor": "rgba(31, 118, 189, 0.18)",
        "full": false,
        "lineColor": "rgb(31, 120, 193)",
        "show": false
      },
      "tableColumn": "instance",
      "targets": [
        {
          "expr": "kafka_controller_kafkacontroller_activecontrollercount_value == 1",
          "format": "table",
          "hide": false,
          "instant": true,
          "interval": "",
          "intervalFactor": 1,
          "legendFormat": "",
          "refId": "A"
        }
      ],
      "thresholds": "",
      "title": "Active controller",
      "type": "singlestat",
      "valueFontSize": "80%",
      "valueMaps": [
        {
          "op": "=",
          "text": "N/A",
          "value": "null"
        }
      ],
      "valueName": "current"
    },
    {
      "cacheTimeout": null,
      "colorBackground": true,
      "colorValue": false,
      "colors": [
        "#d44a3a",
        "rgba(237, 129, 40, 0.89)",
        "#299c46"
      ],
      "datasource": "$datasource",
      "fieldConfig": {
        "defaults": {
          "custom": {}
        },
        "overrides": []
      },
      "format": "none",
      "gauge": {
        "maxValue": 100,
        "minValue": 0,
        "show": false,
        "thresholdLabels": false,
        "thresholdMarkers": true
      },
      "gridPos": {
        "h": 3,
        "w": 4,
        "x": 12,
        "y": 4
      },
      "id": 64,
      "interval": null,
      "links": [],
      "mappingType": 1,
      "mappingTypes": [
        {
          "name": "value to text",
          "value": 1
        },
        {
          "name": "range to text",
          "value": 2
        }
      ],
      "maxDataPoints": 100,
      "nullPointMode": "connected",
      "nullText": null,
      "postfix": "",
      "postfixFontSize": "50%",
      "prefix": "",
      "prefixFontSize": "50%",
      "rangeMaps": [
        {
          "from": "null",
          "text": "N/A",
          "to": "null"
        }
      ],
      "sparkline": {
        "fillColor": "rgba(31, 118, 189, 0.18)",
        "full": false,
        "lineColor": "rgb(31, 120, 193)",
        "show": false
      },
      "tableColumn": "",
      "targets": [
        {
          "expr": "- sum(kafka_server_replicamanager_total_isrexpandspersec_count{instance=~\"$broker\"})",
          "format": "time_series",
          "instant": true,
          "interval": "",
          "intervalFactor": 1,
          "legendFormat": "",
          "refId": "A"
        }
      ],
      "thresholds": "0,0",
      "title": "In-sync replicas expands",
      "type": "singlestat",
      "valueFontSize": "80%",
      "valueMaps": [
        {
          "op": "=",
          "text": "N/A",
          "value": "null"
        }
      ],
      "valueName": "current"
    },
    {
      "cacheTimeout": null,
      "colorBackground": true,
      "colorValue": false,
      "colors": [
        "#299c46",
        "rgba(237, 129, 40, 0.89)",
        "#d44a3a"
      ],
      "datasource": "$datasource",
      "fieldConfig": {
        "defaults": {
          "custom": {}
        },
        "overrides": []
      },
      "format": "none",
      "gauge": {
        "maxValue": 100,
        "minValue": 0,
        "show": false,
        "thresholdLabels": false,
        "thresholdMarkers": true
      },
      "gridPos": {
        "h": 3,
        "w": 4,
        "x": 16,
        "y": 4
      },
      "id": 12,
      "interval": null,
      "links": [],
      "mappingType": 1,
      "mappingTypes": [
        {
          "name": "value to text",
          "value": 1
        },
        {
          "name": "range to text",
          "value": 2
        }
      ],
      "maxDataPoints": 100,
      "nullPointMode": "connected",
      "nullText": null,
      "postfix": "",
      "postfixFontSize": "50%",
      "prefix": "",
      "prefixFontSize": "50%",
      "rangeMaps": [
        {
          "from": "null",
          "text": "N/A",
          "to": "null"
        }
      ],
      "sparkline": {
        "fillColor": "rgba(31, 118, 189, 0.18)",
        "full": false,
        "lineColor": "rgb(31, 120, 193)",
        "show": false
      },
      "tableColumn": "",
      "targets": [
        {
          "expr": "sum(kafka_controller_kafkacontroller_offlinepartitionscount_value{instance=~\"$broker\"})",
          "format": "time_series",
          "instant": true,
          "intervalFactor": 1,
          "refId": "A"
        }
      ],
      "thresholds": "1,1",
      "title": "Offline partitions count",
      "type": "singlestat",
      "valueFontSize": "80%",
      "valueMaps": [
        {
          "op": "=",
          "text": "N/A",
          "value": "null"
        }
      ],
      "valueName": "current"
    },
    {
      "aliasColors": {},
      "bars": false,
      "dashLength": 10,
      "dashes": false,
      "datasource": "$datasource",
      "fieldConfig": {
        "defaults": {
          "custom": {},
          "links": []
        },
        "overrides": []
      },
      "fill": 1,
      "fillGradient": 0,
      "gridPos": {
        "h": 7,
        "w": 8,
        "x": 0,
        "y": 7
      },
      "hiddenSeries": false,
      "id": 16,
      "legend": {
        "avg": false,
        "current": false,
        "max": false,
        "min": false,
        "show": false,
        "total": false,
        "values": false
      },
      "lines": true,
      "linewidth": 2,
      "links": [],
      "nullPointMode": "null",
      "percentage": false,
      "pluginVersion": "7.1.5",
      "pointradius": 5,
      "points": false,
      "renderer": "flot",
      "seriesOverrides": [],
      "spaceLength": 10,
      "stack": false,
      "steppedLine": false,
      "targets": [
        {
          "expr": "kafka_server_brokertopicmetrics_total_bytesinpersec_count{instance=~\"$broker\"} / kafka_server_brokertopicmetrics_total_bytesoutpersec_count{instance=~\"$broker\"}",
          "format": "time_series",
          "hide": false,
          "instant": false,
          "interval": "",
          "intervalFactor": 1,
          "legendFormat": "Broker {{ instance }}",
          "refId": "A"
        }
      ],
      "thresholds": [],
      "timeFrom": null,
      "timeRegions": [],
      "timeShift": null,
      "title": "Bytes rate",
      "tooltip": {
        "shared": true,
        "sort": 0,
        "value_type": "individual"
      },
      "type": "graph",
      "xaxis": {
        "buckets": null,
        "mode": "time",
        "name": null,
        "show": true,
        "values": []
      },
      "yaxes": [
        {
          "format": "Bps",
          "label": null,
          "logBase": 1,
          "max": null,
          "min": null,
          "show": true
        },
        {
          "format": "short",
          "label": null,
          "logBase": 1,
          "max": null,
          "min": null,
          "show": true
        }
      ],
      "yaxis": {
        "align": false,
        "alignLevel": null
      }
    },
    {
      "aliasColors": {},
      "bars": false,
      "dashLength": 10,
      "dashes": false,
      "datasource": "$datasource",
      "fieldConfig": {
        "defaults": {
          "custom": {},
          "links": []
        },
        "overrides": []
      },
      "fill": 1,
      "fillGradient": 0,
      "gridPos": {
        "h": 7,
        "w": 8,
        "x": 8,
        "y": 7
      },
      "hiddenSeries": false,
      "id": 14,
      "legend": {
        "avg": false,
        "current": false,
        "max": false,
        "min": false,
        "show": false,
        "total": false,
        "values": false
      },
      "lines": true,
      "linewidth": 2,
      "links": [],
      "nullPointMode": "null",
      "percentage": false,
      "pluginVersion": "7.1.5",
      "pointradius": 5,
      "points": false,
      "renderer": "flot",
      "seriesOverrides": [],
      "spaceLength": 10,
      "stack": false,
      "steppedLine": false,
      "targets": [
        {
          "expr": "kafka_server_brokertopicmetrics_total_messagesinpersec_oneminuterate{instance=~\"$broker\"}",
          "format": "time_series",
          "instant": false,
          "intervalFactor": 1,
          "legendFormat": "{{ instance }} {{ value }}",
          "refId": "A"
        }
      ],
      "thresholds": [],
      "timeFrom": null,
      "timeRegions": [],
      "timeShift": null,
      "title": "Messages IN",
      "tooltip": {
        "shared": true,
        "sort": 0,
        "value_type": "individual"
      },
      "type": "graph",
      "xaxis": {
        "buckets": null,
        "mode": "time",
        "name": null,
        "show": true,
        "values": []
      },
      "yaxes": [
        {
          "format": "ops",
          "label": null,
          "logBase": 1,
          "max": null,
          "min": null,
          "show": true
        },
        {
          "format": "short",
          "label": null,
          "logBase": 1,
          "max": null,
          "min": null,
          "show": true
        }
      ],
      "yaxis": {
        "align": false,
        "alignLevel": null
      }
    },
    {
      "aliasColors": {},
      "bars": true,
      "dashLength": 10,
      "dashes": false,
      "datasource": "$datasource",
      "fieldConfig": {
        "defaults": {
          "custom": {},
          "links": []
        },
        "overrides": []
      },
      "fill": 1,
      "fillGradient": 0,
      "gridPos": {
        "h": 7,
        "w": 8,
        "x": 16,
        "y": 7
      },
      "hiddenSeries": false,
      "id": 22,
      "legend": {
        "avg": false,
        "current": false,
        "max": false,
        "min": false,
        "show": false,
        "total": false,
        "values": false
      },
      "lines": false,
      "linewidth": 1,
      "links": [],
      "nullPointMode": "null",
      "percentage": false,
      "pluginVersion": "7.1.5",
      "pointradius": 5,
      "points": false,
      "renderer": "flot",
      "seriesOverrides": [],
      "spaceLength": 10,
      "stack": false,
      "steppedLine": false,
      "targets": [
        {
          "expr": "kafka_server_replicamanager_total_partitioncount_value",
          "format": "time_series",
          "instant": true,
          "intervalFactor": 1,
          "legendFormat": "{{ instance }}",
          "refId": "A"
        }
      ],
      "thresholds": [],
      "timeFrom": null,
      "timeRegions": [],
      "timeShift": null,
      "title": "Number of partitions",
      "tooltip": {
        "shared": false,
        "sort": 0,
        "value_type": "individual"
      },
      "type": "graph",
      "xaxis": {
        "buckets": null,
        "mode": "series",
        "name": null,
        "show": true,
        "values": [
          "current"
        ]
      },
      "yaxes": [
        {
          "format": "short",
          "label": null,
          "logBase": 1,
          "max": null,
          "min": "0",
          "show": true
        },
        {
          "format": "short",
          "label": null,
          "logBase": 1,
          "max": null,
          "min": null,
          "show": false
        }
      ],
      "yaxis": {
        "align": false,
        "alignLevel": 0
      }
    },
    {
      "aliasColors": {},
      "bars": false,
      "dashLength": 10,
      "dashes": false,
      "datasource": "$datasource",
      "fieldConfig": {
        "defaults": {
          "custom": {},
          "links": []
        },
        "overrides": []
      },
      "fill": 1,
      "fillGradient": 0,
      "gridPos": {
        "h": 7,
        "w": 8,
        "x": 0,
        "y": 14
      },
      "hiddenSeries": false,
      "id": 55,
      "legend": {
        "avg": false,
        "current": false,
        "max": false,
        "min": false,
        "show": false,
        "total": false,
        "values": false
      },
      "lines": true,
      "linewidth": 2,
      "links": [],
      "nullPointMode": "null",
      "percentage": false,
      "pluginVersion": "7.1.5",
      "pointradius": 5,
      "points": false,
      "renderer": "flot",
      "seriesOverrides": [],
      "spaceLength": 10,
      "stack": false,
      "steppedLine": false,
      "targets": [
        {
          "expr": "rate(kafka_server_brokertopicmetrics_total_bytesinpersec_count{instance=~\"$broker\"}[5m])",
          "format": "time_series",
          "hide": false,
          "instant": false,
          "intervalFactor": 1,
          "legendFormat": "{{ instance }}",
          "refId": "A"
        }
      ],
      "thresholds": [],
      "timeFrom": null,
      "timeRegions": [],
      "timeShift": null,
      "title": "Bytes IN",
      "tooltip": {
        "shared": true,
        "sort": 0,
        "value_type": "individual"
      },
      "type": "graph",
      "xaxis": {
        "buckets": null,
        "mode": "time",
        "name": null,
        "show": true,
        "values": []
      },
      "yaxes": [
        {
          "format": "Bps",
          "label": null,
          "logBase": 1,
          "max": null,
          "min": null,
          "show": true
        },
        {
          "format": "short",
          "label": null,
          "logBase": 1,
          "max": null,
          "min": null,
          "show": true
        }
      ],
      "yaxis": {
        "align": false,
        "alignLevel": null
      }
    },
    {
      "aliasColors": {},
      "bars": false,
      "dashLength": 10,
      "dashes": false,
      "datasource": "$datasource",
      "fieldConfig": {
        "defaults": {
          "custom": {},
          "links": []
        },
        "overrides": []
      },
      "fill": 1,
      "fillGradient": 0,
      "gridPos": {
        "h": 7,
        "w": 8,
        "x": 8,
        "y": 14
      },
      "hiddenSeries": false,
      "id": 56,
      "legend": {
        "avg": false,
        "current": false,
        "max": false,
        "min": false,
        "show": false,
        "total": false,
        "values": false
      },
      "lines": true,
      "linewidth": 2,
      "links": [],
      "nullPointMode": "null",
      "percentage": false,
      "pluginVersion": "7.1.5",
      "pointradius": 5,
      "points": false,
      "renderer": "flot",
      "seriesOverrides": [],
      "spaceLength": 10,
      "stack": false,
      "steppedLine": false,
      "targets": [
        {
          "expr": "rate(kafka_server_brokertopicmetrics_total_bytesoutpersec_count{instance=~\"$broker\"}[5m])",
          "format": "time_series",
          "hide": false,
          "instant": false,
          "intervalFactor": 1,
          "legendFormat": "Broker {{ instance }}",
          "refId": "A"
        }
      ],
      "thresholds": [],
      "timeFrom": null,
      "timeRegions": [],
      "timeShift": null,
      "title": "Bytes OUT",
      "tooltip": {
        "shared": true,
        "sort": 0,
        "value_type": "individual"
      },
      "type": "graph",
      "xaxis": {
        "buckets": null,
        "mode": "time",
        "name": null,
        "show": true,
        "values": []
      },
      "yaxes": [
        {
          "format": "Bps",
          "label": null,
          "logBase": 1,
          "max": null,
          "min": null,
          "show": true
        },
        {
          "format": "short",
          "label": null,
          "logBase": 1,
          "max": null,
          "min": null,
          "show": true
        }
      ],
      "yaxis": {
        "align": false,
        "alignLevel": null
      }
    },
    {
      "aliasColors": {},
      "bars": false,
      "dashLength": 10,
      "dashes": false,
      "datasource": "$datasource",
      "fieldConfig": {
        "defaults": {
          "custom": {},
          "links": []
        },
        "overrides": []
      },
      "fill": 1,
      "fillGradient": 0,
      "gridPos": {
        "h": 7,
        "w": 8,
        "x": 16,
        "y": 14
      },
      "hiddenSeries": false,
      "id": 66,
      "legend": {
        "avg": false,
        "current": false,
        "max": false,
        "min": false,
        "show": false,
        "total": false,
        "values": false
      },
      "lines": true,
      "linewidth": 2,
      "links": [],
      "nullPointMode": "null",
      "percentage": false,
      "pluginVersion": "7.1.5",
      "pointradius": 5,
      "points": false,
      "renderer": "flot",
      "seriesOverrides": [],
      "spaceLength": 10,
      "stack": false,
      "steppedLine": false,
      "targets": [
        {
          "expr": "- kafka_server_replicamanager_total_isrshrinkspersec_count{instance=~\"$broker\"}",
          "format": "time_series",
          "hide": false,
          "intervalFactor": 1,
          "legendFormat": "{{ instance }}",
          "refId": "A"
        },
        {
          "expr": "- kafka_server_replicamanager_total_isrexpandspersec_count{instance=~\"$broker\"}",
          "format": "time_series",
          "hide": true,
          "intervalFactor": 1,
          "legendFormat": "{{ instance }}",
          "refId": "B"
        }
      ],
      "thresholds": [],
      "timeFrom": null,
      "timeRegions": [],
      "timeShift": null,
      "title": "In-sync replicas",
      "tooltip": {
        "shared": true,
        "sort": 0,
        "value_type": "individual"
      },
      "type": "graph",
      "xaxis": {
        "buckets": null,
        "mode": "time",
        "name": null,
        "show": true,
        "values": []
      },
      "yaxes": [
        {
          "format": "short",
          "label": null,
          "logBase": 1,
          "max": "0",
          "min": null,
          "show": true
        },
        {
          "format": "short",
          "label": null,
          "logBase": 1,
          "max": null,
          "min": null,
          "show": true
        }
      ],
      "yaxis": {
        "align": false,
        "alignLevel": null
      }
    },
    {
      "collapsed": false,
      "datasource": "Prometheus",
      "gridPos": {
        "h": 1,
        "w": 24,
        "x": 0,
        "y": 21
      },
      "id": 38,
      "panels": [],
      "title": "JVM",
      "type": "row"
    },
    {
      "aliasColors": {},
      "bars": false,
      "dashLength": 10,
      "dashes": false,
      "datasource": "$datasource",
      "fieldConfig": {
        "defaults": {
          "custom": {},
          "links": []
        },
        "overrides": []
      },
      "fill": 1,
      "fillGradient": 0,
      "gridPos": {
        "h": 7,
        "w": 8,
        "x": 0,
        "y": 22
      },
      "hiddenSeries": false,
      "id": 34,
      "legend": {
        "avg": false,
        "current": false,
        "max": false,
        "min": false,
        "show": false,
        "total": false,
        "values": false
      },
      "lines": true,
      "linewidth": 2,
      "links": [],
      "nullPointMode": "null",
      "percentage": false,
      "pluginVersion": "7.1.5",
      "pointradius": 5,
      "points": false,
      "renderer": "flot",
      "seriesOverrides": [],
      "spaceLength": 10,
      "stack": false,
      "steppedLine": false,
      "targets": [
        {
          "expr": "java_lang_memory_heapmemoryusage_used{instance=~\"$broker\"}",
          "format": "time_series",
          "hide": false,
          "instant": false,
          "interval": "",
          "intervalFactor": 5,
          "legendFormat": "used {{ instance }}",
          "refId": "A"
        },
        {
          "expr": "java_lang_memory_heapmemoryusage_max{instance=~\"$broker\"}",
          "format": "time_series",
          "instant": false,
          "interval": "",
          "intervalFactor": 5,
          "legendFormat": "max {{ instance }}",
          "refId": "B"
        }
      ],
      "thresholds": [],
      "timeFrom": null,
      "timeRegions": [],
      "timeShift": null,
      "title": "JVM memory",
      "tooltip": {
        "shared": true,
        "sort": 0,
        "value_type": "individual"
      },
      "type": "graph",
      "xaxis": {
        "buckets": null,
        "mode": "time",
        "name": null,
        "show": true,
        "values": []
      },
      "yaxes": [
        {
          "format": "decbytes",
          "label": null,
          "logBase": 1,
          "max": null,
          "min": null,
          "show": true
        },
        {
          "format": "short",
          "label": null,
          "logBase": 1,
          "max": null,
          "min": null,
          "show": true
        }
      ],
      "yaxis": {
        "align": false,
        "alignLevel": null
      }
    },
    {
      "aliasColors": {},
      "bars": false,
      "dashLength": 10,
      "dashes": false,
      "datasource": "$datasource",
      "fieldConfig": {
        "defaults": {
          "custom": {},
          "links": []
        },
        "overrides": []
      },
      "fill": 1,
      "fillGradient": 0,
      "gridPos": {
        "h": 7,
        "w": 8,
        "x": 8,
        "y": 22
      },
      "hiddenSeries": false,
      "id": 40,
      "legend": {
        "avg": false,
        "current": false,
        "max": false,
        "min": false,
        "show": false,
        "total": false,
        "values": false
      },
      "lines": true,
      "linewidth": 2,
      "links": [],
      "nullPointMode": "null",
      "percentage": false,
      "pluginVersion": "7.1.5",
      "pointradius": 5,
      "points": false,
      "renderer": "flot",
      "seriesOverrides": [],
      "spaceLength": 10,
      "stack": false,
      "steppedLine": false,
      "targets": [
        {
          "expr": "java_lang_operatingsystem_systemcpuload{instance=~\"$broker\"} * 100",
          "format": "time_series",
          "hide": false,
          "intervalFactor": 4,
          "legendFormat": "system {{ instance }}",
          "refId": "A"
        },
        {
          "expr": "java_lang_operatingsystem_processcpuload{instance=~\"$broker\"} * 100",
          "format": "time_series",
          "hide": false,
          "intervalFactor": 4,
          "legendFormat": "process {{ instance }}",
          "refId": "B"
        }
      ],
      "thresholds": [],
      "timeFrom": null,
      "timeRegions": [],
      "timeShift": null,
      "title": "CPU load",
      "tooltip": {
        "shared": true,
        "sort": 0,
        "value_type": "individual"
      },
      "type": "graph",
      "xaxis": {
        "buckets": null,
        "mode": "time",
        "name": null,
        "show": true,
        "values": []
      },
      "yaxes": [
        {
          "format": "percent",
          "label": null,
          "logBase": 1,
          "max": null,
          "min": null,
          "show": true
        },
        {
          "format": "short",
          "label": null,
          "logBase": 1,
          "max": null,
          "min": null,
          "show": true
        }
      ],
      "yaxis": {
        "align": false,
        "alignLevel": null
      }
    },
    {
      "aliasColors": {},
      "bars": false,
      "dashLength": 10,
      "dashes": false,
      "datasource": "$datasource",
      "fieldConfig": {
        "defaults": {
          "custom": {},
          "links": []
        },
        "overrides": []
      },
      "fill": 1,
      "fillGradient": 0,
      "gridPos": {
        "h": 7,
        "w": 8,
        "x": 16,
        "y": 22
      },
      "hiddenSeries": false,
      "id": 54,
      "legend": {
        "avg": false,
        "current": false,
        "max": false,
        "min": false,
        "show": false,
        "total": false,
        "values": false
      },
      "lines": true,
      "linewidth": 2,
      "links": [],
      "nullPointMode": "null",
      "percentage": false,
      "pluginVersion": "7.1.5",
      "pointradius": 5,
      "points": false,
      "renderer": "flot",
      "seriesOverrides": [],
      "spaceLength": 10,
      "stack": false,
      "steppedLine": false,
      "targets": [
        {
          "expr": "java_lang_operatingsystem_totalphysicalmemorysize{instance=~\"$broker\"}",
          "format": "time_series",
          "intervalFactor": 1,
          "legendFormat": "Total memory {{ instance }}",
          "refId": "A"
        },
        {
          "expr": "java_lang_operatingsystem_freephysicalmemorysize{instance=~\"$broker\"}",
          "format": "time_series",
          "hide": false,
          "intervalFactor": 1,
          "legendFormat": "Free memory {{ instance }}",
          "refId": "B"
        },
        {
          "expr": "java_lang_operatingsystem_totalswapspacesize{instance=~\"$broker\"}",
          "format": "time_series",
          "hide": false,
          "intervalFactor": 1,
          "legendFormat": "Total SWAP  {{ instance }}",
          "refId": "C"
        },
        {
          "expr": "java_lang_operatingsystem_freeswapspacesize{instance=~\"$broker\"}",
          "format": "time_series",
          "hide": false,
          "intervalFactor": 1,
          "legendFormat": "Free SWAP  {{ instance }}",
          "refId": "D"
        },
        {
          "expr": "java_lang_operatingsystem_committedvirtualmemorysize{instance=~\"$broker\"}",
          "format": "time_series",
          "hide": false,
          "intervalFactor": 1,
          "legendFormat": "Committed virtual memory {{ instance }}",
          "refId": "E"
        }
      ],
      "thresholds": [],
      "timeFrom": null,
      "timeRegions": [],
      "timeShift": null,
      "title": "System memory",
      "tooltip": {
        "shared": true,
        "sort": 0,
        "value_type": "individual"
      },
      "type": "graph",
      "xaxis": {
        "buckets": null,
        "mode": "time",
        "name": null,
        "show": true,
        "values": []
      },
      "yaxes": [
        {
          "format": "decbytes",
          "label": null,
          "logBase": 1,
          "max": null,
          "min": null,
          "show": true
        },
        {
          "format": "short",
          "label": null,
          "logBase": 1,
          "max": null,
          "min": null,
          "show": true
        }
      ],
      "yaxis": {
        "align": false,
        "alignLevel": null
      }
    },
    {
      "aliasColors": {},
      "bars": false,
      "dashLength": 10,
      "dashes": false,
      "datasource": "$datasource",
      "fieldConfig": {
        "defaults": {
          "custom": {},
          "links": []
        },
        "overrides": []
      },
      "fill": 1,
      "fillGradient": 0,
      "gridPos": {
        "h": 7,
        "w": 8,
        "x": 0,
        "y": 29
      },
      "hiddenSeries": false,
      "id": 46,
      "legend": {
        "avg": false,
        "current": false,
        "max": false,
        "min": false,
        "show": false,
        "total": false,
        "values": false
      },
      "lines": true,
      "linewidth": 2,
      "links": [],
      "nullPointMode": "null",
      "percentage": false,
      "pluginVersion": "7.1.5",
      "pointradius": 5,
      "points": false,
      "renderer": "flot",
      "seriesOverrides": [],
      "spaceLength": 10,
      "stack": false,
      "steppedLine": false,
      "targets": [
        {
          "expr": "java_lang_operatingsystem_systemloadaverage{instance=~\"$broker\"}",
          "format": "time_series",
          "instant": false,
          "intervalFactor": 1,
          "legendFormat": "System load average",
          "refId": "A"
        },
        {
          "expr": "java_lang_operatingsystem_availableprocessors{instance=~\"$broker\"}",
          "format": "time_series",
          "intervalFactor": 1,
          "legendFormat": "Available Processors",
          "refId": "B"
        }
      ],
      "thresholds": [],
      "timeFrom": null,
      "timeRegions": [],
      "timeShift": null,
      "title": "System load",
      "tooltip": {
        "shared": true,
        "sort": 0,
        "value_type": "individual"
      },
      "type": "graph",
      "xaxis": {
        "buckets": null,
        "mode": "time",
        "name": null,
        "show": true,
        "values": []
      },
      "yaxes": [
        {
          "format": "short",
          "label": null,
          "logBase": 1,
          "max": null,
          "min": null,
          "show": true
        },
        {
          "format": "short",
          "label": null,
          "logBase": 1,
          "max": null,
          "min": null,
          "show": true
        }
      ],
      "yaxis": {
        "align": false,
        "alignLevel": null
      }
    },
    {
      "aliasColors": {},
      "bars": false,
      "dashLength": 10,
      "dashes": false,
      "datasource": "$datasource",
      "fieldConfig": {
        "defaults": {
          "custom": {},
          "links": []
        },
        "overrides": []
      },
      "fill": 1,
      "fillGradient": 0,
      "gridPos": {
        "h": 7,
        "w": 8,
        "x": 8,
        "y": 29
      },
      "hiddenSeries": false,
      "id": 48,
      "legend": {
        "avg": false,
        "current": false,
        "max": false,
        "min": false,
        "show": false,
        "total": false,
        "values": false
      },
      "lines": true,
      "linewidth": 2,
      "links": [],
      "nullPointMode": "null",
      "percentage": false,
      "pluginVersion": "7.1.5",
      "pointradius": 5,
      "points": false,
      "renderer": "flot",
      "seriesOverrides": [],
      "spaceLength": 10,
      "stack": false,
      "steppedLine": false,
      "targets": [
        {
          "expr": "java_lang_operatingsystem_openfiledescriptorcount{instance=~\"$broker\"}",
          "format": "time_series",
          "intervalFactor": 1,
          "legendFormat": "{{ instance }}",
          "refId": "A"
        }
      ],
      "thresholds": [],
      "timeFrom": null,
      "timeRegions": [],
      "timeShift": null,
      "title": "Open file descriptor",
      "tooltip": {
        "shared": true,
        "sort": 0,
        "value_type": "individual"
      },
      "type": "graph",
      "xaxis": {
        "buckets": null,
        "mode": "time",
        "name": null,
        "show": true,
        "values": []
      },
      "yaxes": [
        {
          "format": "short",
          "label": null,
          "logBase": 1,
          "max": null,
          "min": null,
          "show": true
        },
        {
          "format": "short",
          "label": null,
          "logBase": 1,
          "max": null,
          "min": null,
          "show": true
        }
      ],
      "yaxis": {
        "align": false,
        "alignLevel": null
      }
    },
    {
      "cacheTimeout": null,
      "colorBackground": false,
      "colorValue": false,
      "colors": [
        "#299c46",
        "rgba(237, 129, 40, 0.89)",
        "#d44a3a"
      ],
      "datasource": "$datasource",
      "decimals": 0,
      "fieldConfig": {
        "defaults": {
          "custom": {}
        },
        "overrides": []
      },
      "format": "decbytes",
      "gauge": {
        "maxValue": 100,
        "minValue": 0,
        "show": false,
        "thresholdLabels": false,
        "thresholdMarkers": true
      },
      "gridPos": {
        "h": 7,
        "w": 8,
        "x": 16,
        "y": 29
      },
      "id": 44,
      "interval": null,
      "links": [],
      "mappingType": 1,
      "mappingTypes": [
        {
          "name": "value to text",
          "value": 1
        },
        {
          "name": "range to text",
          "value": 2
        }
      ],
      "maxDataPoints": 100,
      "nullPointMode": "connected",
      "nullText": null,
      "postfix": "",
      "postfixFontSize": "50%",
      "prefix": "",
      "prefixFontSize": "50%",
      "rangeMaps": [
        {
          "from": "null",
          "text": "N/A",
          "to": "null"
        }
      ],
      "sparkline": {
        "fillColor": "rgba(31, 118, 189, 0.18)",
        "full": false,
        "lineColor": "rgb(31, 120, 193)",
        "show": false
      },
      "tableColumn": "",
      "targets": [
        {
          "expr": "sum(java_lang_operatingsystem_totalphysicalmemorysize{instance=~\"$broker\"})",
          "format": "time_series",
          "instant": true,
          "intervalFactor": 1,
          "refId": "A"
        }
      ],
      "thresholds": "",
      "title": "Total memory",
      "type": "singlestat",
      "valueFontSize": "80%",
      "valueMaps": [
        {
          "op": "=",
          "text": "N/A",
          "value": "null"
        }
      ],
      "valueName": "current"
    },
    {
      "aliasColors": {},
      "bars": false,
      "dashLength": 10,
      "dashes": false,
      "datasource": "$datasource",
      "fieldConfig": {
        "defaults": {
          "custom": {},
          "links": []
        },
        "overrides": []
      },
      "fill": 1,
      "fillGradient": 0,
      "gridPos": {
        "h": 7,
        "w": 8,
        "x": 0,
        "y": 36
      },
      "hiddenSeries": false,
      "id": 50,
      "legend": {
        "avg": false,
        "current": false,
        "max": false,
        "min": false,
        "show": false,
        "total": false,
        "values": false
      },
      "lines": true,
      "linewidth": 1,
      "links": [],
      "nullPointMode": "null",
      "percentage": false,
      "pluginVersion": "7.1.5",
      "pointradius": 5,
      "points": false,
      "renderer": "flot",
      "seriesOverrides": [],
      "spaceLength": 10,
      "stack": false,
      "steppedLine": false,
      "targets": [
        {
          "expr": "java_lang_classloading_loadedclasscount{instance=~\"$broker\"}",
          "format": "time_series",
          "interval": "",
          "intervalFactor": 1,
          "legendFormat": "Loaded {{ instance }}",
          "refId": "A"
        },
        {
          "expr": "java_lang_classloading_loadedclasscount_total{instance=~\"$broker\"}",
          "format": "time_series",
          "interval": "",
          "intervalFactor": 1,
          "legendFormat": "Total loaded {{ instance }}",
          "refId": "B"
        },
        {
          "expr": "java_lang_classloading_loadedclasscount_total{instance=~\"$broker\"}",
          "format": "time_series",
          "interval": "",
          "intervalFactor": 1,
          "legendFormat": "Unloaded {{ instance }}",
          "refId": "C"
        },
        {
          "expr": "delta(java_lang_classloading_loadedclasscount{instance=~\"$broker\"}[5m])",
          "format": "time_series",
          "interval": "",
          "intervalFactor": 1,
          "legendFormat": "Delta {{ instance }}",
          "refId": "D"
        }
      ],
      "thresholds": [],
      "timeFrom": null,
      "timeRegions": [],
      "timeShift": null,
      "title": "Class loading",
      "tooltip": {
        "shared": true,
        "sort": 0,
        "value_type": "individual"
      },
      "type": "graph",
      "xaxis": {
        "buckets": null,
        "mode": "time",
        "name": null,
        "show": true,
        "values": []
      },
      "yaxes": [
        {
          "format": "short",
          "label": null,
          "logBase": 1,
          "max": null,
          "min": null,
          "show": true
        },
        {
          "format": "short",
          "label": null,
          "logBase": 1,
          "max": null,
          "min": null,
          "show": true
        }
      ],
      "yaxis": {
        "align": false,
        "alignLevel": null
      }
    },
    {
      "aliasColors": {},
      "bars": false,
      "dashLength": 10,
      "dashes": false,
      "datasource": "$datasource",
      "fieldConfig": {
        "defaults": {
          "custom": {},
          "links": []
        },
        "overrides": []
      },
      "fill": 1,
      "fillGradient": 0,
      "gridPos": {
        "h": 7,
        "w": 8,
        "x": 8,
        "y": 36
      },
      "hiddenSeries": false,
      "id": 52,
      "legend": {
        "avg": false,
        "current": false,
        "max": false,
        "min": false,
        "show": false,
        "total": false,
        "values": false
      },
      "lines": true,
      "linewidth": 2,
      "links": [],
      "nullPointMode": "null",
      "percentage": false,
      "pluginVersion": "7.1.5",
      "pointradius": 5,
      "points": false,
      "renderer": "flot",
      "seriesOverrides": [],
      "spaceLength": 10,
      "stack": false,
      "steppedLine": false,
      "targets": [
        {
          "expr": "java_lang_threading_threadcount{instance=~\"$broker\"}",
          "format": "time_series",
          "interval": "",
          "intervalFactor": 1,
          "legendFormat": "Current {{ instance }}",
          "refId": "A"
        },
        {
          "expr": "java_lang_threading_daemonthreadcount{instance=~\"$broker\"}",
          "format": "time_series",
          "interval": "",
          "intervalFactor": 1,
          "legendFormat": "Daemon {{ instance }}",
          "refId": "B"
        },
        {
          "expr": "java_lang_threading_peakthreadcount{instance=~\"$broker\"}",
          "format": "time_series",
          "interval": "",
          "intervalFactor": 1,
          "legendFormat": "Peak {{ instance }}",
          "refId": "D"
        },
        {
          "expr": "java_lang_threading_totalstartedthreadcount{instance=~\"$broker\"}",
          "format": "time_series",
          "interval": "",
          "intervalFactor": 1,
          "legendFormat": "Started total {{ instance }}",
          "refId": "E"
        }
      ],
      "thresholds": [],
      "timeFrom": null,
      "timeRegions": [],
      "timeShift": null,
      "title": "Threads",
      "tooltip": {
        "shared": true,
        "sort": 0,
        "value_type": "individual"
      },
      "type": "graph",
      "xaxis": {
        "buckets": null,
        "mode": "time",
        "name": null,
        "show": true,
        "values": []
      },
      "yaxes": [
        {
          "format": "short",
          "label": null,
          "logBase": 1,
          "max": null,
          "min": null,
          "show": true
        },
        {
          "format": "short",
          "label": null,
          "logBase": 1,
          "max": null,
          "min": null,
          "show": true
        }
      ],
      "yaxis": {
        "align": false,
        "alignLevel": null
      }
    },
    {
      "cacheTimeout": null,
      "colorBackground": false,
      "colorValue": false,
      "colors": [
        "#299c46",
        "rgba(237, 129, 40, 0.89)",
        "#d44a3a"
      ],
      "datasource": "$datasource",
      "fieldConfig": {
        "defaults": {
          "custom": {}
        },
        "overrides": []
      },
      "format": "none",
      "gauge": {
        "maxValue": 100,
        "minValue": 0,
        "show": false,
        "thresholdLabels": false,
        "thresholdMarkers": true
      },
      "gridPos": {
        "h": 7,
        "w": 8,
        "x": 16,
        "y": 36
      },
      "id": 42,
      "interval": null,
      "links": [],
      "mappingType": 1,
      "mappingTypes": [
        {
          "name": "value to text",
          "value": 1
        },
        {
          "name": "range to text",
          "value": 2
        }
      ],
      "maxDataPoints": 100,
      "nullPointMode": "connected",
      "nullText": null,
      "postfix": "",
      "postfixFontSize": "50%",
      "prefix": "",
      "prefixFontSize": "50%",
      "rangeMaps": [
        {
          "from": "null",
          "text": "N/A",
          "to": "null"
        }
      ],
      "sparkline": {
        "fillColor": "rgba(31, 118, 189, 0.18)",
        "full": false,
        "lineColor": "rgb(31, 120, 193)",
        "show": false
      },
      "tableColumn": "",
      "targets": [
        {
          "expr": "sum(java_lang_operatingsystem_availableprocessors{instance=~\"$broker\"})",
          "format": "time_series",
          "instant": true,
          "interval": "",
          "intervalFactor": 1,
          "legendFormat": "",
          "refId": "A"
        }
      ],
      "thresholds": "",
      "title": "Total CPUs",
      "type": "singlestat",
      "valueFontSize": "80%",
      "valueMaps": [
        {
          "op": "=",
          "text": "N/A",
          "value": "null"
        }
      ],
      "valueName": "current"
    },
    {
      "collapsed": false,
      "datasource": "Prometheus",
      "gridPos": {
        "h": 1,
        "w": 24,
        "x": 0,
        "y": 43
      },
      "id": 73,
      "panels": [],
      "title": "Details",
      "type": "row"
    },
    {
      "aliasColors": {},
      "bars": false,
      "dashLength": 10,
      "dashes": false,
      "datasource": "$datasource",
      "fieldConfig": {
        "defaults": {
          "custom": {},
          "links": []
        },
        "overrides": []
      },
      "fill": 1,
      "fillGradient": 0,
      "gridPos": {
        "h": 7,
        "w": 8,
        "x": 0,
        "y": 44
      },
      "hiddenSeries": false,
      "id": 61,
      "legend": {
        "avg": false,
        "current": false,
        "max": false,
        "min": false,
        "show": false,
        "total": false,
        "values": false
      },
      "lines": true,
      "linewidth": 2,
      "links": [],
      "nullPointMode": "null",
      "percentage": false,
      "pluginVersion": "7.1.5",
      "pointradius": 5,
      "points": false,
      "renderer": "flot",
      "seriesOverrides": [],
      "spaceLength": 10,
      "stack": false,
      "steppedLine": false,
      "targets": [
        {
          "expr": "kafka_network_requestmetrics_requestspersec_count{instance=~\"$broker\", request=\"Produce\"}",
          "format": "time_series",
          "hide": false,
          "interval": "",
          "intervalFactor": 1,
          "legendFormat": "{{ instance }} produce",
          "refId": "A"
        },
        {
          "expr": "kafka_network_requestmetrics_requestspersec_count{instance=~\"$broker\", request=\"FetchConsumer\"}",
          "format": "time_series",
          "interval": "",
          "intervalFactor": 1,
          "legendFormat": "{{ instance }} fetch consumer",
          "refId": "B"
        },
        {
          "expr": " kafka_network_requestmetrics_requestspersec_count{instance=~\"$broker\", request=\"FetchFollower\"}",
          "format": "time_series",
          "interval": "",
          "intervalFactor": 1,
          "legendFormat": "{{ instance }} fetch follower",
          "refId": "C"
        }
      ],
      "thresholds": [],
      "timeFrom": null,
      "timeRegions": [],
      "timeShift": null,
      "title": "Number of requests",
      "tooltip": {
        "shared": true,
        "sort": 0,
        "value_type": "individual"
      },
      "type": "graph",
      "xaxis": {
        "buckets": null,
        "mode": "time",
        "name": null,
        "show": true,
        "values": []
      },
      "yaxes": [
        {
          "format": "reqps",
          "label": null,
          "logBase": 1,
          "max": null,
          "min": null,
          "show": true
        },
        {
          "format": "short",
          "label": null,
          "logBase": 1,
          "max": null,
          "min": null,
          "show": true
        }
      ],
      "yaxis": {
        "align": false,
        "alignLevel": null
      }
    },
    {
      "aliasColors": {},
      "bars": false,
      "dashLength": 10,
      "dashes": false,
      "datasource": "$datasource",
      "fieldConfig": {
        "defaults": {
          "custom": {},
          "links": []
        },
        "overrides": []
      },
      "fill": 1,
      "fillGradient": 0,
      "gridPos": {
        "h": 7,
        "w": 8,
        "x": 8,
        "y": 44
      },
      "hiddenSeries": false,
      "id": 75,
      "legend": {
        "avg": false,
        "current": false,
        "max": false,
        "min": false,
        "show": false,
        "total": false,
        "values": false
      },
      "lines": true,
      "linewidth": 2,
      "links": [],
      "nullPointMode": "null",
      "percentage": false,
      "pluginVersion": "7.1.5",
      "pointradius": 5,
      "points": false,
      "renderer": "flot",
      "seriesOverrides": [],
      "spaceLength": 10,
      "stack": false,
      "steppedLine": false,
      "targets": [
        {
          "expr": "kafka_server_delayedoperationpurgatory_numdelayedoperations_fetch_value{instance=~\"$broker\"}",
          "format": "time_series",
          "intervalFactor": 4,
          "legendFormat": "{{ instance }}",
          "refId": "A"
        }
      ],
      "thresholds": [],
      "timeFrom": null,
      "timeRegions": [],
      "timeShift": null,
      "title": "Purgatory delayed fetch operations",
      "tooltip": {
        "shared": true,
        "sort": 0,
        "value_type": "individual"
      },
      "type": "graph",
      "xaxis": {
        "buckets": null,
        "mode": "time",
        "name": null,
        "show": true,
        "values": []
      },
      "yaxes": [
        {
          "format": "short",
          "label": null,
          "logBase": 1,
          "max": null,
          "min": null,
          "show": true
        },
        {
          "format": "short",
          "label": null,
          "logBase": 1,
          "max": null,
          "min": null,
          "show": true
        }
      ],
      "yaxis": {
        "align": false,
        "alignLevel": null
      }
    },
    {
      "aliasColors": {},
      "bars": false,
      "dashLength": 10,
      "dashes": false,
      "datasource": "$datasource",
      "fieldConfig": {
        "defaults": {
          "custom": {},
          "links": []
        },
        "overrides": []
      },
      "fill": 1,
      "fillGradient": 0,
      "gridPos": {
        "h": 7,
        "w": 8,
        "x": 16,
        "y": 44
      },
      "hiddenSeries": false,
      "id": 71,
      "legend": {
        "avg": false,
        "current": false,
        "max": false,
        "min": false,
        "show": false,
        "total": false,
        "values": false
      },
      "lines": true,
      "linewidth": 2,
      "links": [],
      "nullPointMode": "null",
      "percentage": false,
      "pluginVersion": "7.1.5",
      "pointradius": 5,
      "points": false,
      "renderer": "flot",
      "seriesOverrides": [],
      "spaceLength": 10,
      "stack": false,
      "steppedLine": false,
      "targets": [
        {
          "expr": "sum (kafka_log_log_size) by(instance)",
          "format": "time_series",
          "intervalFactor": 1,
          "legendFormat": "{{ instance }}",
          "refId": "A"
        }
      ],
      "thresholds": [],
      "timeFrom": null,
      "timeRegions": [],
      "timeShift": null,
      "title": "Log size by broker",
      "tooltip": {
        "shared": true,
        "sort": 0,
        "value_type": "individual"
      },
      "type": "graph",
      "xaxis": {
        "buckets": null,
        "mode": "time",
        "name": null,
        "show": true,
        "values": []
      },
      "yaxes": [
        {
          "format": "decbytes",
          "label": null,
          "logBase": 1,
          "max": null,
          "min": null,
          "show": true
        },
        {
          "format": "short",
          "label": null,
          "logBase": 1,
          "max": null,
          "min": null,
          "show": true
        }
      ],
      "yaxis": {
        "align": false,
        "alignLevel": null
      }
    },
    {
      "aliasColors": {},
      "bars": false,
      "dashLength": 10,
      "dashes": false,
      "datasource": "$datasource",
      "fieldConfig": {
        "defaults": {
          "custom": {},
          "links": []
        },
        "overrides": []
      },
      "fill": 1,
      "fillGradient": 0,
      "gridPos": {
        "h": 7,
        "w": 8,
        "x": 0,
        "y": 51
      },
      "hiddenSeries": false,
      "id": 18,
      "legend": {
        "avg": false,
        "current": false,
        "max": false,
        "min": false,
        "show": false,
        "total": false,
        "values": false
      },
      "lines": true,
      "linewidth": 2,
      "links": [],
      "nullPointMode": "null",
      "percentage": false,
      "pluginVersion": "7.1.5",
      "pointradius": 5,
      "points": false,
      "renderer": "flot",
      "seriesOverrides": [],
      "spaceLength": 10,
      "stack": false,
      "steppedLine": false,
      "targets": [
        {
          "expr": "sum(kafka_network_requestmetrics_requestspersec_count{instance=~\"$broker\"}) by (request)",
          "format": "time_series",
          "intervalFactor": 1,
          "legendFormat": "{{ request }}",
          "refId": "A"
        }
      ],
      "thresholds": [],
      "timeFrom": null,
      "timeRegions": [],
      "timeShift": null,
      "title": "All number of requests",
      "tooltip": {
        "shared": true,
        "sort": 0,
        "value_type": "individual"
      },
      "type": "graph",
      "xaxis": {
        "buckets": null,
        "mode": "time",
        "name": null,
        "show": true,
        "values": []
      },
      "yaxes": [
        {
          "format": "reqps",
          "label": null,
          "logBase": 1,
          "max": null,
          "min": null,
          "show": true
        },
        {
          "format": "short",
          "label": null,
          "logBase": 1,
          "max": null,
          "min": null,
          "show": true
        }
      ],
      "yaxis": {
        "align": false,
        "alignLevel": null
      }
    },
    {
      "aliasColors": {},
      "bars": false,
      "dashLength": 10,
      "dashes": false,
      "datasource": "$datasource",
      "description": "The average fraction of time the network processors are idle",
      "fieldConfig": {
        "defaults": {
          "custom": {},
          "links": []
        },
        "overrides": []
      },
      "fill": 0,
      "fillGradient": 0,
      "gridPos": {
        "h": 7,
        "w": 8,
        "x": 8,
        "y": 51
      },
      "hiddenSeries": false,
      "id": 68,
      "legend": {
        "avg": false,
        "current": false,
        "max": false,
        "min": false,
        "show": false,
        "total": false,
        "values": false
      },
      "lines": true,
      "linewidth": 2,
      "links": [],
      "nullPointMode": "null",
      "percentage": false,
      "pluginVersion": "7.1.5",
      "pointradius": 5,
      "points": false,
      "renderer": "flot",
      "seriesOverrides": [],
      "spaceLength": 10,
      "stack": false,
      "steppedLine": false,
      "targets": [
        {
          "expr": "kafka_network_processor_idlepercent_value{instance=~\"$broker\"}",
          "format": "time_series",
          "hide": false,
          "instant": false,
          "intervalFactor": 1,
          "legendFormat": "{{ instance }} network processor {{ network_processor }}",
          "refId": "A"
        }
      ],
      "thresholds": [
        {
          "colorMode": "critical",
          "fill": true,
          "line": true,
          "op": "lt",
          "value": 0.3,
          "yaxis": "left"
        }
      ],
      "timeFrom": null,
      "timeRegions": [],
      "timeShift": null,
      "title": "Idle network processors",
      "tooltip": {
        "shared": true,
        "sort": 0,
        "value_type": "individual"
      },
      "type": "graph",
      "xaxis": {
        "buckets": null,
        "mode": "time",
        "name": null,
        "show": true,
        "values": []
      },
      "yaxes": [
        {
          "format": "short",
          "label": null,
          "logBase": 1,
          "max": null,
          "min": "0",
          "show": true
        },
        {
          "format": "short",
          "label": null,
          "logBase": 1,
          "max": null,
          "min": null,
          "show": true
        }
      ],
      "yaxis": {
        "align": true,
        "alignLevel": null
      }
    },
    {
      "aliasColors": {},
      "bars": false,
      "dashLength": 10,
      "dashes": false,
      "datasource": "$datasource",
      "description": "The average fraction of time the request handler threads are idle",
      "fieldConfig": {
        "defaults": {
          "custom": {},
          "links": []
        },
        "overrides": []
      },
      "fill": 0,
      "fillGradient": 0,
      "gridPos": {
        "h": 7,
        "w": 8,
        "x": 16,
        "y": 51
      },
      "hiddenSeries": false,
      "id": 69,
      "legend": {
        "avg": false,
        "current": false,
        "max": false,
        "min": false,
        "show": false,
        "total": false,
        "values": false
      },
      "lines": true,
      "linewidth": 2,
      "links": [],
      "nullPointMode": "null",
      "percentage": false,
      "pluginVersion": "7.1.5",
      "pointradius": 5,
      "points": false,
      "renderer": "flot",
      "seriesOverrides": [],
      "spaceLength": 10,
      "stack": false,
      "steppedLine": false,
      "targets": [
        {
          "expr": "kafka_server_kafkarequesthandlerpool_total_requesthandleravgidlepercent_oneminuterate{instance=~\"$broker\"}",
          "format": "time_series",
          "hide": false,
          "instant": false,
          "intervalFactor": 1,
          "legendFormat": "{{ instance }}",
          "refId": "A"
        }
      ],
      "thresholds": [
        {
          "colorMode": "critical",
          "fill": true,
          "line": true,
          "op": "lt",
          "value": 0.3,
          "yaxis": "left"
        }
      ],
      "timeFrom": null,
      "timeRegions": [],
      "timeShift": null,
      "title": "Idle request handler threads",
      "tooltip": {
        "shared": true,
        "sort": 0,
        "value_type": "individual"
      },
      "type": "graph",
      "xaxis": {
        "buckets": null,
        "mode": "time",
        "name": null,
        "show": true,
        "values": []
      },
      "yaxes": [
        {
          "format": "short",
          "label": null,
          "logBase": 1,
          "max": null,
          "min": "0",
          "show": true
        },
        {
          "format": "short",
          "label": null,
          "logBase": 1,
          "max": null,
          "min": null,
          "show": true
        }
      ],
      "yaxis": {
        "align": true,
        "alignLevel": null
      }
    }
  ],
  "refresh": "1m",
  "schemaVersion": 26,
  "style": "dark",
  "tags": [],
  "templating": {
    "list": [
      {
        "current": {
          "selected": false,
          "text": "Prometheus",
          "value": "Prometheus"
        },
        "hide": 0,
        "includeAll": false,
        "label": null,
        "multi": false,
        "name": "datasource",
        "options": [],
        "query": "prometheus",
        "queryValue": "",
        "refresh": 1,
        "regex": "",
        "skipUrlSync": false,
        "type": "datasource"
      },
      {
        "allValue": ".*:5556$",
        "current": {
          "selected": false,
          "text": "my-kafka-cluster",
          "value": "my-kafka-cluster"
        },
        "datasource": "$datasource",
        "definition": "label_values(kafka_controller_kafkacontroller_activecontrollercount_value, instance)",
        "hide": 0,
        "includeAll": true,
        "label": null,
        "multi": false,
        "name": "broker",
        "options": [],
        "query": "label_values(kafka_controller_kafkacontroller_activecontrollercount_value, instance)",
        "refresh": 2,
        "regex": "",
        "skipUrlSync": false,
        "sort": 1,
        "tagValuesQuery": "",
        "tags": [],
        "tagsQuery": "",
        "type": "query",
        "useTags": false
      }
    ]
  },
  "time": {
    "from": "now-30m",
    "to": "now"
  },
  "timepicker": {
    "refresh_intervals": [
      "5s",
      "10s",
      "30s",
      "1m",
      "5m",
      "15m",
      "30m",
      "1h",
      "2h",
      "1d"
    ],
    "time_options": [
      "5m",
      "15m",
      "1h",
      "6h",
      "12h",
      "24h",
      "2d",
      "7d",
      "30d"
    ]
  },
  "timezone": "",
  "title": "Kubernetes Kafka",
  "uid": "kafka",
  "version": 4
}
